musiclm_pytorch/__init__.py
musiclm_pytorch/distributed.py
musiclm_pytorch/musiclm_pytorch.py
musiclm_pytorch/trainer.py
musiclm_pytorch-0.2.8.dist-info/LICENSE
musiclm_pytorch-0.2.8.dist-info/METADATA
musiclm_pytorch-0.2.8.dist-info/WHEEL
musiclm_pytorch-0.2.8.dist-info/top_level.txt
musiclm_pytorch-0.2.8.dist-info/RECORD
