Metadata-Version: 2.1
Name: musiclm-pytorch
Version: 0.2.8
Summary: MusicLM - AudioLM + Audio CLIP to text to music synthesis
Home-page: https://github.com/lucidrains/musiclm-pytorch
Author: Phil Wang
Author-email: lucidrains@gmail.com
License: MIT
Keywords: artificial intelligence,deep learning,transformers,attention mechanism,text to music,contrastive learning
Classifier: Development Status :: 4 - Beta
Classifier: Intended Audience :: Developers
Classifier: Topic :: Scientific/Engineering :: Artificial Intelligence
Classifier: License :: OSI Approved :: MIT License
Classifier: Programming Language :: Python :: 3.6
License-File: LICENSE
Requires-Dist: accelerate
Requires-Dist: audiolm-pytorch >=0.17.0
Requires-Dist: beartype
Requires-Dist: einops >=0.6
Requires-Dist: lion-pytorch
Requires-Dist: vector-quantize-pytorch >=1.0.0
Requires-Dist: x-clip
Requires-Dist: torch >=1.12
Requires-Dist: torchaudio
